{
    "dark": {
        "surface": {
            "level-0": { "value": "#090909" },
            "level-1": { "value": "#1a1a1a" },
            "level-2": { "value": "#222222" },
            "level-1-hover": {
                "value": "color-mix(\n        in srgb,\n        var(--surface-level-1) 90%,\n        var(--colour-text) 10%\n    )"
            },
            "level-1-active": {
                "value": "color-mix(\n        in srgb,\n        var(--surface-level-1) 80%,\n        var(--colour-text) 20%\n    )"
            }
        },
        "colour": {
            "text": { "value": "#f5f5f5" },
            "text-subtle": { "value": "#b3b3b3" },
            "border": { "value": "#333333" },
            "muted": { "value": "#2a2a2a" },
            "primary": {
                "value": "#b0a3ff",
                "hover": {
                    "value": "color-mix(\n        in srgb,\n        var(--colour-primary) 90%,\n        var(--colour-on-primary) 10%\n    )"
                },
                "active": {
                    "value": "color-mix(\n        in srgb,\n        var(--colour-primary) 80%,\n        var(--colour-on-primary) 20%\n    )"
                }
            },
            "on-primary": { "value": "#000000" },
            "success": { "value": "#2fdd88" },
            "warning": { "value": "#ffcb33" },
            "danger": { "value": "#ff6b6b" }
        }
    }
}
